minddatapack/__init__.py
minddatapack/arweaveconnector.py
minddatapack/ipfsconnector.py
minddatapack/localfileconnector.py
minddatapack/mindlakeconnector.py
minddatapack/utils.py
minddatapack/web3storageconnector.py
minddatapack-1.0.3.dist-info/METADATA
minddatapack-1.0.3.dist-info/WHEEL
minddatapack-1.0.3.dist-info/licenses/LICENSE
minddatapack-1.0.3.dist-info/RECORD
