Metadata-Version: 2.1
Name: minddatapack
Version: 1.0.3
Summary: A Python SDK to migrate data between Mind Lake and other storages
Project-URL: Homepage, https://github.com/mind-network/mind-datapack-python
Project-URL: Bug Tracker, https://github.com/mind-network/mind-datapack-python/issues
Author-email: Mind Labs <biz@mindnetwork.xyz>
License-File: LICENSE
Keywords: datalake,encryption,web3
Classifier: License :: OSI Approved :: MIT License
Classifier: Operating System :: OS Independent
Classifier: Programming Language :: Python :: 3
Requires-Python: >=3.8
Requires-Dist: arseeding
Requires-Dist: mindlakesdk
